{"hash":"1a682ddbf04119b3ae5b33fa6198693c16efb750","data":{"wordPressPostTag":{"title":"template","belongsTo":{"pageInfo":{"totalPages":2,"currentPage":2},"edges":[{"node":{"id":"1149","title":"Template: Pingbacks And Trackbacks","path":"/2012/01/01/template-pingbacks-an-trackbacks/","excerpt":"<p>This post has many pingpacks and trackbacks. There are a few ways to list them. Above the comments Below the comments Included within the normal flow of comments</p>\n"}},{"node":{"id":"1151","title":"Edge Case: Many Tags","path":"/2009/06/01/edge-case-many-tags/","excerpt":"<p>This post has many tags.</p>\n"}}]}}},"context":{}}